MANIFEST.in
README.rst
setup.py
todd/__init__.py
todd/main.py
todd.egg-info/PKG-INFO
todd.egg-info/SOURCES.txt
todd.egg-info/dependency_links.txt
todd.egg-info/entry_points.txt
todd.egg-info/requires.txt
todd.egg-info/top_level.txt
todd/tasklib/__init__.py
todd/tasklib/task.py
todd/tasklib/tasklist.py
todd/tasklib/util.py
todd/tasklib/test/__init__.py
todd/tasklib/test/todo_test.py
todd/taskui/__init__.py
todd/taskui/colorscheme.py
todd/taskui/components.py
todd/taskui/keys.py
todd/taskui/main_help.py
todd/taskui/main_ui.py
todd/taskui/taskitem.py
todd/taskui/colors/default