Metadata-Version: 1.2
Name: todd
Version: 0.0.5
Summary: An interactive terminal based todo.txt file editor
Home-page: https://github.com/laktak/todd
Author: Christian Zangl
Author-email: laktak@cdak.net
License: UNKNOWN
Keywords: todotxt,todo.txt,todo,terminal,urwid,curses,console
Platform: UNKNOWN
Classifier: Development Status :: 4 - Beta
Classifier: Environment :: Console :: Curses
Classifier: Intended Audience :: End Users/Desktop
Classifier: License :: OSI Approved :: GNU General Public License v3 (GPLv3)
Classifier: Natural Language :: English
Classifier: Operating System :: POSIX :: Linux
Classifier: Operating System :: MacOS
Classifier: Programming Language :: Python :: 3.6
Classifier: Topic :: Office/Business :: Scheduling
Requires-Python: >=3.6.0
